git_toggle/__init__.py
git_toggle/__main__.py
git_toggle/py.typed
git_toggle-0.1.2.dist-info/LICENSE
git_toggle-0.1.2.dist-info/METADATA
git_toggle-0.1.2.dist-info/WHEEL
git_toggle-0.1.2.dist-info/entry_points.txt
git_toggle-0.1.2.dist-info/RECORD
