Metadata-Version: 2.2
Name: git-toggle
Version: 0.1.2
Summary: Toggle Git remotes between https and ssh.
Author-email: Dominic Davis-Foster <dominic@davis-foster.co.uk>
License: MIT
Keywords: git
Home-page: https://github.com/domdfcoding/git-toggle
Project-URL: Issue Tracker, https://github.com/domdfcoding/git-toggle/issues
Project-URL: Source Code, https://github.com/domdfcoding/git-toggle
Project-URL: Documentation, https://git-toggle.readthedocs.io/en/latest
Platform: Windows
Platform: macOS
Platform: Linux
Classifier: Development Status :: 4 - Beta
Classifier: Environment :: Console
Classifier: Intended Audience :: Developers
Classifier: License :: OSI Approved :: MIT License
Classifier: Operating System :: OS Independent
Classifier: Programming Language :: Python
Classifier: Programming Language :: Python :: 3 :: Only
Classifier: Programming Language :: Python :: 3.7
Classifier: Programming Language :: Python :: 3.8
Classifier: Programming Language :: Python :: 3.9
Classifier: Programming Language :: Python :: 3.10
Classifier: Programming Language :: Python :: 3.11
Classifier: Programming Language :: Python :: 3.12
Classifier: Programming Language :: Python :: 3.13
Classifier: Programming Language :: Python :: Implementation :: CPython
Classifier: Programming Language :: Python :: Implementation :: PyPy
Classifier: Topic :: Software Development :: Version Control :: Git
Classifier: Topic :: Utilities
Classifier: Typing :: Typed
Requires-Python: >=3.7
Requires-Dist: apeye-core>=1.0.0
Requires-Dist: attrs>=20.3.0
Requires-Dist: click>=7.1.2
Requires-Dist: consolekit>=1.0.0
Requires-Dist: domdf-python-tools>=0.8.3
Requires-Dist: dulwich>=0.19.16
Requires-Dist: southwark>=0.7.0
Requires-Dist: typing-extensions>=3.7.4.3
